README.md
setup.py
LibHus/IntroPy.py
LibHus/Telegram.py
LibHus.egg-info/PKG-INFO
LibHus.egg-info/SOURCES.txt
LibHus.egg-info/dependency_links.txt
LibHus.egg-info/requires.txt
LibHus.egg-info/top_level.txt